examples/__init__.py
examples/run.py
flexidata/Logger.py
flexidata/__init__.py
flexidata/config/__init__.py
flexidata/config/config.py
flexidata/models/__init__.py
flexidata/models/base.py
flexidata/models/detectron2.py
flexidata/ocr/__init__.py
flexidata/ocr/agent.py
flexidata/ocr/google_vision.py
flexidata/ocr/paddle.py
flexidata/ocr/tesseract.py
flexidata/parser/__init__.py
flexidata/parser/doc.py
flexidata/parser/document.py
flexidata/parser/docx.py
flexidata/parser/epub.py
flexidata/parser/html.py
flexidata/parser/image.py
flexidata/parser/md.py
flexidata/parser/odt.py
flexidata/parser/org.py
flexidata/parser/pdf.py
flexidata/parser/ppt.py
flexidata/parser/pptx.py
flexidata/parser/rst.py
flexidata/parser/rtf.py
flexidata/parser/xlsx.py
flexidata/preprocessor/__init__.py
flexidata/preprocessor/base.py
flexidata/reader/__init__.py
flexidata/reader/factory.py
flexidata/reader/file_reader.py
flexidata/reader/google_drive.py
flexidata/reader/handlers.py
flexidata/reader/local.py
flexidata/reader/s3.py
flexidata/reader/web.py
flexidata/text_processing/__init__.py
flexidata/text_processing/classification.py
flexidata/text_processing/convert_file.py
flexidata/text_processing/text_block.py
flexidata/utils/__init__.py
flexidata/utils/common.py
flexidata/utils/constants.py
flexidata/utils/decorators.py
flexidata/utils/pdf.py
flexidata/utils/tables.py
flexidata/utils/text.py
tests/__init__.py
tests/ocr/__init__.py
tests/ocr/test_agent.py
tests/utils/__init__.py
tests/utils/test_common.py
flexidata-0.0.19.dist-info/LICENSE
flexidata-0.0.19.dist-info/METADATA
flexidata-0.0.19.dist-info/WHEEL
flexidata-0.0.19.dist-info/top_level.txt
flexidata-0.0.19.dist-info/RECORD
