Metadata-Version: 2.1
Name: flexidata
Version: 0.0.19
Summary: FlexiData is an open-source Python package designed for processing unstructured data.
Author-email: Kalyanakannan Padivasu <Kalyanakannan.p@gmail.com>
License: Apache License
Project-URL: Homepage, https://github.com/flexidatalabs/flexidata
Project-URL: Issues, https://github.com/flexidatalabs/flexidata/issues
Keywords: PDF,DOCX document parsing
Classifier: Programming Language :: Python :: 3
Classifier: License :: OSI Approved :: Apache Software License
Classifier: Operating System :: OS Independent
Requires-Python: >=3.9
License-File: LICENSE
Requires-Dist: python-dotenv ==1.0.1
Requires-Dist: pdfplumber ==0.11.0
Requires-Dist: pdf2image ==1.17.0
Requires-Dist: poppler-utils ==0.1.0
Requires-Dist: pillow ==10.3.0
Requires-Dist: numpy ==1.26.4
Requires-Dist: scipy ==1.13.0
Requires-Dist: layoutparser ==0.3.4
Requires-Dist: torch ==2.2.2
Requires-Dist: torchvision ==0.17.2
Requires-Dist: pdfminer.six ==20231228
Requires-Dist: typing ==3.7.4.3
Requires-Dist: rapidocr-onnxruntime ==1.3.17
Requires-Dist: PyMuPDF ==1.24.2
Requires-Dist: nltk ==3.8.1
Requires-Dist: langdetect ==1.0.9
Requires-Dist: PyDrive ==1.3.1
Requires-Dist: boto3 ==1.34.102
Requires-Dist: requests ==2.31.0
Requires-Dist: pytesseract ==0.3.10
Requires-Dist: paddlepaddle ==2.6.1
Requires-Dist: paddlepaddle-gpu ==2.6.1
Requires-Dist: paddleocr ==2.7.3
Requires-Dist: google-cloud-vision ==3.7.2
Requires-Dist: python-docx ==1.1.2
Requires-Dist: tabulate ==0.9.0
Requires-Dist: lxml ==5.2.2
Requires-Dist: python-pptx ==0.6.23
Requires-Dist: Markdown ==3.6
Requires-Dist: pypandoc ==1.13
